rocketx/providers/impala/__init__.py
rocketx/providers/impala/get_provider_info.py
rocketx/providers/impala/hooks/__init__.py
rocketx/providers/impala/hooks/impala.py
rocketx_providers_impala-0.1.0.dist-info/entry_points.txt
rocketx_providers_impala-0.1.0.dist-info/WHEEL
rocketx_providers_impala-0.1.0.dist-info/METADATA
rocketx_providers_impala-0.1.0.dist-info/RECORD
